Workbook

Sheet Sheet1
A1: Date | B1: Username | C1: JobName | D1: SubJobName | E1: StartTime | F1: EndTime | G1: Hrs | H1: Description | I1: Tag | J1: Maintenance | K1: CMT Testing | L1: New Request
A2: 46204 | B2: Benjie | C2: TBS_PRG | D2: JUN2026 | E2: 1.5569444 | F2: 1.5756944 | G2: 0.45 | H2: JUN2026: cont. adjusting the import template sheet | I2: New | L2: =IF(I2="New",G2,0) -> 0.45
A3: 46204 | B3: Reymart | C3: TBS_CALENDAR | D3: MAINTENANCE | E3: 1.4465278 | F3: 1.5340278 | G3: 2.1 | H3: Bug Fix: Filing Type - FT_055 -Audit: Created By / Date captured, Action By was not captured | J3: =IF(I3="New",0,G3-K3) -> 0.6 | K3: 1.5 | L3: =IF(I3="New",G3,0) -> 0
A4: 46204 | B4: Reymart | C4: TBS_CALENDAR | D4: MAINTENANCE | E4: 1.7541667 | F4: 1.8451389 | G4: 2.183333 | H4: Bug Fix: Holiday - HOL_008 - Delete unused holiday Deleted unused holiday still appears in the holiday list | J4: =IF(I4="New",0,G4-K4) -> 1.383333 | K4: 0.8 | L4: =IF(I4="New",G4,0) -> 0
A5: 46204 | B5: Reymart | C5: TBS_CALENDAR | D5: MAINTENANCE | E5: 1.5340278 | F5: 1.6208333 | G5: 2.083333 | H5: Bug Fix: Filing Type - FT_056 - Audit: Updated By / Date captured Action By was not captured | J5: =IF(I5="New",0,G5-K5) -> 1.083333 | K5: 1 | L5: =IF(I5="New",G5,0) -> 0
A6: 46204 | B6: Reymart | C6: TBS_CALENDAR | D6: MAINTENANCE | E6: 1.6652778 | F6: 1.7541667 | G6: 2.133333 | H6: Bug Fix: State - ST_016 - Cities are displayed in a single continuous list without pagination features | J6: =IF(I6="New",0,G6-K6) -> 0.533333 | K6: 1.6 | L6: =IF(I6="New",G6,0) -> 0
A7: 46205 | B7: Reymart | C7: TBS_CALENDAR | D7: MAINTENANCE | E7: 1.5305556 | F7: 1.6194444 | G7: 2.133333 | H7: Bug Fix: UL-008 - The system successfully generates a new temporary password, but it fails to mask it by default | J7: =IF(I7="New",0,G7-K7) -> 0.633333 | K7: 1.5 | L7: =IF(I7="New",G7,0) -> 0
A8: 46205 | B8: Reymart | C8: TBS_CALENDAR | D8: MAINTENANCE | E8: 1.6652778 | F8: 1.7534722 | G8: 2.116666 | H8: Bug Fix: Users List - UL-012 - Agent role – assign Processor/Preparer/Filer | J8: =IF(I8="New",0,G8-K8) -> 0.716666 | K8: 1.4 | L8: =IF(I8="New",G8,0) -> 0
A9: 46205 | B9: Reymart | C9: TBS_CALENDAR | D9: MAINTENANCE | E9: 1.4402778 | F9: 1.5305556 | G9: 2.166666 | H9: Bug Fix: Holiday - HOL_010 - Audit tracking on add/edit/delete/clone | J9: =IF(I9="New",0,G9-K9) -> 0.966666 | K9: 1.2 | L9: =IF(I9="New",G9,0) -> 0
A10: 46205 | B10: Reymart | C10: TBS_CALENDAR | D10: MAINTENANCE | E10: 1.7534722 | F10: 1.8465278 | G10: 2.233333 | H10: Bug Fix: Users List - UL-013 - Assistant Manager role assignment, Data Display Mismatch users filing roles | J10: =IF(I10="New",0,G10-K10) -> 0.633333 | K10: 1.6 | L10: =IF(I10="New",G10,0) -> 0
A11: 46206 | B11: Reymart | C11: TBS_CALENDAR | D11: MAINTENANCE | E11: 1.5659722 | F11: 1.6541667 | G11: 2.116666 | H11: Bug Fix: UL-016 Supervisor role assignment - The Users Search Result grid incorrectly displays "Processor" in list | J11: =IF(I11="New",0,G11-K11) -> 0.816666 | K11: 1.3 | L11: =IF(I11="New",G11,0) -> 0
A12: 46206 | B12: Reymart | C12: TBS_CALENDAR | D12: MAINTENANCE | E12: 1.7041667 | F12: 1.7909722 | G12: 2.083333 | H12: Bug Fix: ST_021 - States - Add / Edit / Delete - Delete City was not captured | J12: =IF(I12="New",0,G12-K12) -> 0.883333 | K12: 1.2 | L12: =IF(I12="New",G12,0) -> 0
A13: 46206 | B13: Reymart | C13: TBS_CALENDAR | D13: MAINTENANCE | E13: 1.4756944 | F13: 1.5659722 | G13: 2.166666 | H13: Bug Fix: UL-015 - The Users Search Result grid incorrectly displays "Processor" in the user's filing role list | J13: =IF(I13="New",0,G13-K13) -> 1.466666 | K13: 0.7 | L13: =IF(I13="New",G13,0) -> 0
A14: 46206 | B14: Reymart | C14: TBS_CALENDAR | D14: MAINTENANCE | E14: 1.7909722 | F14: 1.8791667 | G14: 2.116666 | H14: Bug Fix: Filing Type - FT_020 - Start date did not automatically change after changing the frequency | J14: =IF(I14="New",0,G14-K14) -> 1.416666 | K14: 0.7 | L14: =IF(I14="New",G14,0) -> 0
... A18: 46209 | B18: Reymart | C18: TBS_CALENDAR | D18: 2026JULY | E18: 1.4756944 | F18: 1.5638889 | G18: 2.116666 | H18: Bug Fix: ST - City - Delete City was not captured | J18: =IF(I18="New",0,G18-K18) -> 1.316666 | K18: 0.8 | L18: =IF(I18="New",G18,0) -> 0
A19: 46209 | B19: Benjie | C19: TBS_PRG | D19: 2026JUL | E19: 1.6895833 | F19: 1.7284722 | G19: 0.933333 | H19: 2026JUL: work on the adjustment for setting up the template sheet. | I19: New | L19: =IF(I19="New",G19,0) -> 0.933333
A20: 46209 | B20: Benjie | C20: TBS_PRG | D20: 2026JUL | E20: 1.7284722 | F20: 1.7729167 | G20: 1.066666 | H20: 2026JUL: cont.. working on the adjustment for setting up the template sheet. | I20: New | L20: =IF(I20="New",G20,0) -> 1.066666
A21: 46209 | B21: Benjie | C21: TBS_PRG | D21: 2026JUL | E21: 1.8368056 | F21: 1.8902778 | G21: 1.283333 | H21: 2026JUL: cont.. working on the adjustment for setting up the template sheet. | I21: New | L21: =IF(I21="New",G21,0) -> 1.283333
A22: 46210 | B22: Benjie | C22: TBS_PRG | D22: 2026JUL | E22: 1.7486111 | F22: 1.7708333 | G22: 0.533333 | H22: 2026JUL: JUN2026: working on the displaying of state, from states module and its interaction with others | I22: New | L22: =IF(I22="New",G22,0) -> 0.533333
A23: 46210 | B23: Benjie | C23: TBS_PRG | D23: 2026JUL | E23: 1.8631944 | F23: 1.9083333 | G23: 1.083333 | H23: 2026JUL: Work on the affected parts when only allowing to display the state with tax rates on other modules | I23: New | L23: =IF(I23="New",G23,0) -> 1.083333
A24: 46210 | B24: Benjie | C24: TBS_PRG | D24: 2026JUL | E24: 1.9083333 | F24: 1.9520833 | G24: 1.05 | H24: 2026JUL: Cont.. working on the affected parts when only allowing to display the state with tax rates on other modules | I24: New | L24: =IF(I24="New",G24,0) -> 1.05
A25: 46210 | B25: Benjie | C25: TBS_PRG | D25: 2026JUL | E25: 1.9520833 | F25: 1.9993056 | G25: 1.133333 | H25: 2026JUL: Cont.. working on the affected parts when only allowing to display the state with tax rates on other modules | I25: New | L25: =IF(I25="New",G25,0) -> 1.133333
A26: 46210 | B26: Reymart | C26: TBS_CALENDAR | D26: 2026JULY | E26: 1.5236111 | F26: 1.6125 | G26: 2.133333 | H26: Bug Fix: FT - Filing Types - Removed the validation for detecting existing forms when importing new forms and filings | J26: =IF(I26="New",0,G26-K26) -> 1.433333 | K26: 0.7 | L26: =IF(I26="New",G26,0) -> 0
A27: 46210 | B27: Reymart | C27: TBS_CALENDAR | D27: 2026JULY | E27: 1.6645833 | F27: 1.7548611 | G27: 2.166666 | H27: Bug Fix: Sales & Use Tax - CST/RVWS Gross Allocation - Enabled the Total Amount field for Managers role | J27: =IF(I27="New",0,G27-K27) -> 1.266666 | K27: 0.9 | L27: =IF(I27="New",G27,0) -> 0
A28: 46210 | B28: Reymart | C28: TBS_CALENDAR | D28: 2026JULY | E28: 1.4319444 | F28: 1.5236111 | G28: 2.2 | H28: Bug Fix: FT Filing Types - When importing filings for other BU, error message saying form already exists was encountered | J28: =IF(I28="New",0,G28-K28) -> 0.9 | K28: 1.3 | L28: =IF(I28="New",G28,0) -> 0
A29: 46210 | B29: Reymart | C29: TBS_CALENDAR | D29: 2026JULY | E29: 1.7548611 | F29: 1.8402778 | G29: 2.05 | H29: Bug Fix: Filing Website - Enhanced the import process to support updating existing data using the re-import process | J29: =IF(I29="New",0,G29-K29) -> 1.35 | K29: 0.7 | L29: =IF(I29="New",G29,0) -> 0
A30: 46211 | B30: Benjie | C30: TBS_PRG | D30: 2026JUL | E30: 1.4673611 | F30: 1.4944444 | G30: 0.65 | H30: Worked on the committing of changes. Aggregate similar changes. | J30: =IF(I30="New",0,G30-K30) -> 0.65 | L30: =IF(I30="New",G30,0) -> 0
A31: 46211 | B31: Reymart | C31: TBS_CALENDAR | D31: 2026JULY | E31: 1.7395833 | F31: 1.8305556 | G31: 2.183333 | H31: Bug Fix: FT_020 - Added function 'processMonthAndDayValuesForSavingEditForm' that get the exact date | J31: =IF(I31="New",0,G31-K31) -> 1.383333 | K31: 0.8 | L31: =IF(I31="New",G31,0) -> 0
A32: 46211 | B32: Benjie | C32: TBS_PRG | D32: 2026JUL | E32: 1.0111111 | F32: 1.0520833 | G32: 0.983333 | H32: 2026JUL: Cont.. working on the affected parts when only allowing to display the state with tax rates on other modules | I32: New | L32: =IF(I32="New",G32,0) -> 0.983333
A33: 46211 | B33: Reymart | C33: TBS_CALENDAR | D33: 2026JULY | E33: 1.5131944 | F33: 1.6006944 | G33: 2.1 | H33: Bug Fix: FT_020 - Added new sections for date fields based on the selected frequency. | J33: =IF(I33="New",0,G33-K33) -> 0.8 | K33: 1.3 | L33: =IF(I33="New",G33,0) -> 0
A34: 46211 | B34: Reymart | C34: TBS_CALENDAR | D34: 2026JULY | E34: 1.6520833 | F34: 1.7395833 | G34: 2.1 | H34: Bug Fix: FT_020 - Added function 'loadFilingPeriodEditForm_change' that properly populates dates based on frequency | J34: =IF(I34="New",0,G34-K34) -> 0.8 | K34: 1.3 | L34: =IF(I34="New",G34,0) -> 0
A35: 46211 | B35: Reymart | C35: TBS_CALENDAR | D35: 2026JULY | E35: 1.4236111 | F35: 1.5131944 | G35: 2.15 | H35: Bug Fix: FT_020 - Start Date recalculated by Frequency | J35: =IF(I35="New",0,G35-K35) -> 0.55 | K35: 1.6 | L35: =IF(I35="New",G35,0) -> 0
A36: 46211 | B36: Benjie | C36: TBS_PRG | D36: 2026JUL | E36: 1.5611111 | F36: 1.6486111 | G36: 2.1 | H36: 2026JUL: working on the fix for locking of invoices. Change the locking on completed invoices. | I36: New | L36: =IF(I36="New",G36,0) -> 2.1
A37: 46211 | B37: Benjie | C37: TBS_PRG | D37: 2026JUL | E37: 1.7805556 | F37: 1.8034722 | G37: 0.55 | H37: 2026JUL: working on the assignment issue on the define jurisdiction name for geocode and tax category. | I37: New | L37: =IF(I37="New",G37,0) -> 0.55
A38: 46211 | B38: Benjie | C38: TBS_PRG | D38: 2026JUL | E38: 1.8958333 | F38: 1.9166667 | G38: 0.5 | H38: 2026JUL: development update meeting on synergy with tbs and binc team. | J38: =IF(I38="New",0,G38-K38) -> 0.5 | L38: =IF(I38="New",G38,0) -> 0
A39: 46212 | B39: Reymart | C39: TBS_CALENDAR | D39: 2026JULY | E39: 1.6715278 | F39: 1.7590278 | G39: 2.1 | H39: Bug Fix: Import Gross and Tax Amount - Enhanced the function 'getState' and ensured they are trimmed before being used | J39: =IF(I39="New",0,G39-K39) -> 1 | K39: 1.1 | L39: =IF(I39="New",G39,0) -> 0
A40: 46212 | B40: Benjie | C40: TBS_PRG | D40: 2026JUL | E40: 1.1152778 | F40: 1.1645833 | G40: 1.183333 | H40: 2026JUL: Reviewing the issue on discrepancy the zainab sent this is for the nov 2024 | J40: =IF(I40="New",0,G40-K40) -> 1.183333 | L40: =IF(I40="New",G40,0) -> 0
A41: 46212 | B41: Benjie | C41: TBS_PRG | D41: 2026JUL | E41: 1.1013889 | F41: 1.1152778 | G41: 0.333333 | H41: 2026JUL: working on the ngtypeahead of the dropdown. | J41: 0.333333 | L41: =IF(I41="New",G41,0) -> 0
A42: 46212 | B42: Benjie | C42: TBS_PRG | D42: 2026JUL | E42: 1.6069444 | F42: 1.64375 | G42: 0.883333 | H42: Cont. reviewing the 12-2024, 03-2025 & 05-2025 period mentioned that has some discrepancy. | J42: =IF(I42="New",0,G42-K42) -> 0.883333 | L42: =IF(I42="New",G42,0) -> 0
A43: 46212 | B43: Reymart | C43: TBS_CALENDAR | D43: 2026JULY | E43: 1.5784722 | F43: 1.6715278 | G43: 2.233333 | H43: Conducted debugging in the DevTools section of main.js in CMT Tax Calendar test site 8091 to capture the exact issue | J43: =IF(I43="New",0,G43-K43) -> 1.033333 | K43: 1.2 | L43: =IF(I43="New",G43,0) -> 0
A44: 46212 | B44: Benjie | C44: TBS_PRG | D44: 2026JUL | E44: 1.6777778 | F44: 1.7402778 | G44: 1.5 | H44: Cont. reviewing the 12-2024, 03-2025 & 05-2025 period mentioned that has some discrepancy. | J44: =IF(I44="New",0,G44-K44) -> 1.5 | L44: =IF(I44="New",G44,0) -> 0
A45: 46213 | B45: Benjie | C45: TBS_PRG | D45: 2026JUL | E45: 1 | F45: 1.05 | G45: 1.2 | H45: 2026JUL: work on the adding of new vertex setting for geocode or tax category of non existing setting. | I45: New | L45: =IF(I45="New",G45,0) -> 1.2
A46: 46213 | B46: Benjie | C46: TBS_PRG | D46: 2026JUL | E46: 1.05 | F46: 1.1034722 | G46: 1.283333 | H46: 2026JUL: cont.. working on the adding of new vertex setting for geocode or tax category of non existing setting. | I46: New | L46: =IF(I46="New",G46,0) -> 1.283333
A47: 46214 | B47: Benjie | C47: TBS_PRG | D47: 2026JUL | E47: 1.5840278 | F47: 1.6659722 | G47: 1.966666 | H47: 2026JUL: work on the event & function. Tried adding the validation and fixing any bugs on the saving | I47: New | L47: =IF(I47="New",G47,0) -> 1.966666
A48: 46214 | B48: Benjie | C48: TBS_PRG | D48: 2026JUL | E48: 1.7395833 | F48: 1.7743056 | G48: 0.833333 | H48: 2026JUL: fixing the data for the vertex setting of import template. Saving to db the name for those without jurisdiction | I48: New | L48: =IF(I48="New",G48,0) -> 0.833333
A49: 46214 | B49: Benjie | C49: TBS_PRG | D49: 2026JUL | E49: 1.875 | F49: 1.9659722 | G49: 2.183333 | H49: 2026JUL: work on the data. Seeding the default reporting location. Add columns on vertexsetting, default location, | I49: New | L49: =IF(I49="New",G49,0) -> 2.183333
A50: 46216 | B50: Benjie | C50: TBS_CALENDAR | D50: 2026JULY | E50: 1.7347222 | F50: 1.7888889 | G50: 1.3 | H50: Investigate and fix issue on wy not matching the imported amount from sales tax calc tool. | J50: =IF(I50="New",0,G50-K50) -> 0.5 | K50: 0.8 | L50: =IF(I50="New",G50,0) -> 0
A51: 46216 | B51: Benjie | C51: TBS_CALENDAR | D51: 2026JULY | E51: 1.7888889 | F51: 1.8243056 | G51: 0.85 | H51: Cont. working on the issues from filter not working on tax calendar, the filing setup not displaying. | J51: 0.85 | L51: =IF(I51="New",G51,0) -> 0
A52: 46216 | B52: Chelle | C52: TBS_CALENDAR | D52: 2026JULY | E52: 1.59375 | F52: 1.6458333 | G52: 1.25 | H52: Investigate new issues, mostly caused by filing types not setup properly | J52: =IF(I52="New",0,G52-K52) -> 0.55 | K52: 0.7 | L52: =IF(I52="New",G52,0) -> 0
A53: 46216 | B53: Reymart | C53: TBS_CALENDAR | D53: 2026JULY | E53: 1.7375 | F53: 1.8270833 | G53: 2.15 | H53: Bug Fix - Prompt Tax: Assigned the exact qtr start and end dates to New York state filings with a quarterly frequency | J53: =IF(I53="New",0,G53-K53) -> 1.05 | K53: 1.1 | L53: =IF(I53="New",G53,0) -> 0
A54: 46216 | B54: Benjie | C54: TBS_CALENDAR | D54: 2026JULY | E54: 1.8409722 | F54: 1.8659722 | G54: 0.6 | H54: Cont. working on the issues from filter not working on tax calendar, the filing setup not displaying. | J54: 0.6 | L54: =IF(I54="New",G54,0) -> 0
A55: 46216 | B55: Reymart | C55: TBS_CALENDAR | D55: 2026JULY | E55: 1.6506944 | F55: 1.7375 | G55: 2.083333 | H55: Bug Fix - Prompt Tax: Added a new function in the controller API to filter those filings with a quarterly frequency | J55: =IF(I55="New",0,G55-K55) -> 1.083333 | K55: 1 | L55: =IF(I55="New",G55,0) -> 0
A56: 46217 | B56: Benjie | C56: TBS_PRG | D56: 2026JUL | E56: 1.4451389 | F56: 1.48125 | G56: 0.866666 | H56: 2026JUL: working on the import template settings. Changing the behavior of enabling of state | I56: New | L56: =IF(I56="New",G56,0) -> 0.866666
A57: 46217 | B57: Benjie | C57: TBS_PRG | D57: 2026JUL | E57: 1.5215278 | F57: 1.5722222 | G57: 1.216666 | H57: 2026JUL: cont. working on the import template settings. Changing the behavior of enabling of state | I57: New | L57: =IF(I57="New",G57,0) -> 1.216666
A58: 46217 | B58: Benjie | C58: TBS_PRG | D58: 2026JUL | E58: 1.5722222 | F58: 1.6263889 | G58: 1.3 | H58: 2026JUL: cont. working on the import template settings. Changing the behavior of enabling of state | I58: New | L58: =IF(I58="New",G58,0) -> 1.3
A59: 46217 | B59: Benjie | C59: TBS_PRG | D59: 2026JUL | E59: 1.6263889 | F59: 1.6659722 | G59: 0.95 | H59: 2026JUL: creating 2 endpoint for single and multiple enabling/disabling of import template setting | I59: New | L59: =IF(I59="New",G59,0) -> 0.95
A60: 46217 | B60: Reymart | C60: TBS_CALENDAR | D60: 2026JULY | E60: 1.5222222 | F60: 1.6069444 | G60: 2.033333 | H60: Bug Fix - FT: Enhanced the function 'compose-data-for-updating-form.ts' to ensure clean data before importing forms | J60: =IF(I60="New",0,G60-K60) -> 1.033333 | K60: 1 | L60: =IF(I60="New",G60,0) -> 0
A61: 46217 | B61: Reymart | C61: TBS_CALENDAR | D61: 2026JULY | E61: 1.7409722 | F61: 1.8284722 | G61: 2.1 | H61: Bug Fix - FT: Improved the security of form deletion by adding validation for debit limit/bank account linked to FormId | J61: =IF(I61="New",0,G61-K61) -> 0.6 | K61: 1.5 | L61: =IF(I61="New",G61,0) -> 0
A62: 46217 | B62: Reymart | C62: TBS_CALENDAR | D62: 2026JULY | E62: 1.4319444 | F62: 1.5222222 | G62: 2.166666 | H62: Bug Fix - FT: Enhanced the function 'compose-data-for-creating-form.ts' to ensure clean data before importing forms | J62: =IF(I62="New",0,G62-K62) -> 1.166666 | K62: 1 | L62: =IF(I62="New",G62,0) -> 0
A63: 46217 | B63: Reymart | C63: TBS_CALENDAR | D63: 2026JULY | E63: 1.6548611 | F63: 1.7409722 | G63: 2.066666 | H63: Bug Fix - FT: Applied a feature that allows importing the same forms again for use under another company | J63: =IF(I63="New",0,G63-K63) -> 1.266666 | K63: 0.8 | L63: =IF(I63="New",G63,0) -> 0
A64: 46218 | B64: Reymart | C64: TBS_CALENDAR | D64: 2026JULY | E64: 1.4354167 | F64: 1.5243056 | G64: 2.133333 | H64: Bug Fix - BA_016: Updated the implementation of privileges for the Admin role on the bank account page | J64: =IF(I64="New",0,G64-K64) -> 1.033333 | K64: 1.1 | L64: =IF(I64="New",G64,0) -> 0
A65: 46218 | B65: Reymart | C65: TBS_CALENDAR | D65: 2026JULY | E65: 1.7444444 | F65: 1.8326389 | G65: 2.116666 | H65: Bug Fix - ST_016: Updated city-search.service.ts by adding the onPageChange and onPageSizeChanged functions | J65: =IF(I65="New",0,G65-K65) -> 0.516666 | K65: 1.6 | L65: =IF(I65="New",G65,0) -> 0
A66: 46218 | B66: Benjie | C66: TBS_PRG | D66: 2026JUL | E66: 1.5743056 | F66: 1.6493056 | G66: 1.8 | H66: Working on the impor template setting mapping of the states on the audit report setting. | I66: New | L66: =IF(I66="New",G66,0) -> 1.8
A67: 46218 | B67: Benjie | C67: TBS_PRG | D67: 2026JUL | E67: 1.6493056 | F67: 1.6729167 | G67: 0.566666 | H67: Working on the state module associate states. | I67: New | L67: =IF(I67="New",G67,0) -> 0.566666
A68: 46218 | B68: Benjie | C68: TBS_PRG | D68: 2026JUL | E68: 1.7131944 | F68: 1.7611111 | G68: 1.15 | H68: Cont. working on the state module associate states. | I68: New | L68: =IF(I68="New",G68,0) -> 1.15
A69: 46218 | B69: Reymart | C69: TBS_CALENDAR | D69: 2026JULY | E69: 1.5243056 | F69: 1.6097222 | G69: 2.05 | H69: Bug Fix - BA_016: Applied the privileges for the Assistant Manager role on the bank account page | J69: =IF(I69="New",0,G69-K69) -> 1.25 | K69: 0.8 | L69: =IF(I69="New",G69,0) -> 0
A70: 46218 | B70: Reymart | C70: TBS_CALENDAR | D70: 2026JULY | E70: 1.6548611 | F70: 1.7444444 | G70: 2.15 | H70: Bug Fix - ST_016: Updated the city-search.service.ts by adding logic for filtering with pagination when loading data | J70: =IF(I70="New",0,G70-K70) -> 1.45 | K70: 0.7 | L70: =IF(I70="New",G70,0) -> 0
A71: 46219 | B71: Benjie | C71: TBS_PRG | D71: 2026JUL | E71: 1.0076389 | F71: 1.0520833 | G71: 1.066666 | H71: 2026JUL: work on the behavior for adding of company jurisdiction, adjusted the form for adding of new company | I71: New | L71: =IF(I71="New",G71,0) -> 1.066666
A72: 46219 | B72: Reymart | C72: TBS_CALENDAR | D72: 2026JULY | E72: 1.4243056 | F72: 1.5145833 | G72: 2.166666 | H72: Bug Fix - ST_016: Updated the vmCity$ combineLatest function by adding a total counter and pager instance | J72: =IF(I72="New",0,G72-K72) -> 1.266666 | K72: 0.9 | L72: =IF(I72="New",G72,0) -> 0
A73: 46219 | B73: Reymart | C73: TBS_CALENDAR | D73: 2026JULY | E73: 1.7375 | F73: 1.8243056 | G73: 2.083333 | H73: Bug Fix - HOL_006: Enhanced data handling for nullable values before using them in each condition in the backend API | J73: =IF(I73="New",0,G73-K73) -> 0.583333 | K73: 1.5 | L73: =IF(I73="New",G73,0) -> 0
A74: 46219 | B74: Reymart | C74: TBS_CALENDAR | D74: 2026JULY | E74: 1.6479167 | F74: 1.7375 | G74: 2.15 | H74: Bug Fix - HOL_006: Added validation to all required fields before triggering the submit function | J74: =IF(I74="New",0,G74-K74) -> 1.35 | K74: 0.8 | L74: =IF(I74="New",G74,0) -> 0
A75: 46219 | B75: Benjie | C75: TBS_PRG | D75: 2026JUL | E75: 1.0520833 | F75: 1.0958333 | G75: 1.05 | H75: 2026JUL: cont. working on the behavior for adding of company jurisdiction, adjusted the form for adding of new company | I75: New | L75: =IF(I75="New",G75,0) -> 1.05
A76: 46219 | B76: Benjie | C76: TBS_PRG | D76: 2026JUL | E76: 1.0958333 | F76: 1.1548611 | G76: 1.416666 | H76: 2026JUL: working on the flow for adding/editing of jurisdiction & create delete function | I76: New | L76: =IF(I76="New",G76,0) -> 1.416666
A77: 46219 | B77: Reymart | C77: TBS_CALENDAR | D77: 2026JULY | E77: 1.5145833 | F77: 1.6020833 | G77: 2.1 | H77: Bug Fix - ST_016: Improved the City List UI by adding pagination and enhancing the scrolling overflow design | J77: =IF(I77="New",0,G77-K77) -> 0.7 | K77: 1.4 | L77: =IF(I77="New",G77,0) -> 0
A78: 46220 | B78: Benjie | C78: TBS_PRG | D78: 2026JUL | E78: 1.0604167 | F78: 1.1263889 | G78: 1.583333 | H78: 2026JUL: works on the not admin display of import tempalate setting. | I78: New | L78: =IF(I78="New",G78,0) -> 1.583333
A79: 46220 | B79: Reymart | C79: TBS_CALENDAR | D79: 2026JULY | E79: 1.6583333 | F79: 1.74375 | G79: 2.05 | H79: Bug Fix -LGN-022: Enhanced the EmailController by handling SendMail response and properly using the message response | J79: =IF(I79="New",0,G79-K79) -> 0.85 | K79: 1.2 | L79: =IF(I79="New",G79,0) -> 0
A80: 46220 | B80: Benjie | C80: TBS_PRG | D80: 2026JUL | E80: 1.6270833 | F80: 1.6694444 | G80: 1.016666 | H80: Works on the associate states for the state module & applying the parent ui adjustments. | I80: New | L80: =IF(I80="New",G80,0) -> 1.016666
A81: 46220 | B81: Reymart | C81: TBS_CALENDAR | D81: 2026JULY | E81: 1.5256944 | F81: 1.6138889 | G81: 2.116666 | H81: Bug Fix -LGN-022: Updated EmailerService.cs by changing the SendMail return value to a boolean data type | J81: =IF(I81="New",0,G81-K81) -> 1.116666 | K81: 1 | L81: =IF(I81="New",G81,0) -> 0
A82: 46220 | B82: Benjie | C82: TBS_PRG | D82: 2026JUL | E82: 1.6694444 | F82: 1.7111111 | G82: 1 | H82: Cont.. working on the associate states for the state module & applying the parent ui adjustments. | I82: New | L82: =IF(I82="New",G82,0) -> 1
A83: 46220 | B83: Reymart | C83: TBS_CALENDAR | D83: 2026JULY | E83: 1.4395833 | F83: 1.5256944 | G83: 2.066666 | H83: Bug Fix - FT_026: Added Vertex company code as a required field and included it in the validation when saving data | J83: =IF(I83="New",0,G83-K83) -> 0.966666 | K83: 1.1 | L83: =IF(I83="New",G83,0) -> 0
A84: 46220 | B84: Reymart | C84: TBS_CALENDAR | D84: 2026JULY | E84: 1.74375 | F84: 1.8326389 | G84: 2.133333 | H84: Bug Fix -LGN-022: Changed the condition for handling SendMail response in payment approval process within AuthController | J84: =IF(I84="New",0,G84-K84) -> 1.433333 | K84: 0.7 | L84: =IF(I84="New",G84,0) -> 0
A85: 46223 | B85: Reymart | C85: TBS_CALENDAR | D85: 2026JULY | E85: 1.6013889 | F85: 1.6909722 | G85: 2.15 | H85: Tax Calendar: Improved calendarFilingController sorting by adding null checks to prevent errors in condition logic | J85: =IF(I85="New",0,G85-K85) -> 1.15 | K85: 1 | L85: =IF(I85="New",G85,0) -> 0
A86: 46223 | B86: Reymart | C86: TBS_CALENDAR | D86: 2026JULY | E86: 1.7375 | F86: 1.8256944 | G86: 2.116666 | H86: Bug Fix - FT_043: Import valid Calendar Filings batch- Fix saving issue for “Is Generated from Sales Tax” field | J86: =IF(I86="New",0,G86-K86) -> 0.916666 | K86: 1.2 | L86: =IF(I86="New",G86,0) -> 0
A87: 46223 | B87: Reymart | C87: TBS_CALENDAR | D87: 2026JULY | E87: 1.8256944 | F87: 1.9111111 | G87: 2.05 | H87: Filing Type Enhancements: Disable the cells that no need to update in the generated import file | J87: =IF(I87="New",0,G87-K87) -> 1.25 | K87: 0.8 | L87: =IF(I87="New",G87,0) -> 0
A88: 46224 | B88: Benjie | C88: TBS_PRG | D88: 2026JUL | E88: 1.65625 | F88: 1.6993056 | G88: 1.033333 | H88: Cont working on the update for the backend of tax rule updating | I88: New | L88: =IF(I88="New",G88,0) -> 1.033333
A89: 46224 | B89: Benjie | C89: TBS_PRG | D89: 2026JUL | E89: 1.5923611 | F89: 1.6361111 | G89: 1.05 | H89: working on the approach I should apply on the single document tax rule. | J89: =IF(I89="New",0,G89-K89) -> 1.05 | L89: =IF(I89="New",G89,0) -> 0
A90: 46224 | B90: Benjie | C90: TBS_PRG | D90: 2026JUL | E90: 1.6993056 | F90: 1.7631944 | G90: 1.533333 | H90: Cont working on the update for the backend of tax rule updating | J90: =IF(I90="New",0,G90-K90) -> 1.533333 | L90: =IF(I90="New",G90,0) -> 0
A91: 46224 | B91: Benjie | C91: TBS_PRG | D91: 2026JUL | E91: 1.0458333 | F91: 1.0958333 | G91: 1.2 | H91: 2026JUL: investigate the missing td of the invoice document & adjusting the data on it. | J91: =IF(I91="New",0,G91-K91) -> 1.2 | L91: =IF(I91="New",G91,0) -> 0
A92: 46224 | B92: Reymart | C92: TBS_CALENDAR | D92: 2026JULY | E92: 1.5506944 | F92: 1.6375 | G92: 2.083333 | H92: Filing Type Enhancements: Modified 'generate-template-for-updating-form.ts' added function that can protect Excel sheet | J92: =IF(I92="New",0,G92-K92) -> 0.583333 | K92: 1.5 | L92: =IF(I92="New",G92,0) -> 0
A93: 46224 | B93: Reymart | C93: TBS_CALENDAR | D93: 2026JULY | E93: 1.8652778 | F93: 1.9534722 | G93: 2.116666 | H93: Bug Fix - FT_026 Open Filings: Enhanced filing-type frontend by adding conditional logic to display company code or name | J93: =IF(I93="New",0,G93-K93) -> 0.816666 | K93: 1.3 | L93: =IF(I93="New",G93,0) -> 0
A94: 46224 | B94: Benjie | C94: TBS_PRG | D94: 2026JUL | E94: 1.5506944 | F94: 1.5923611 | G94: 1 | H94: 2026JUL: works on the issue of activity log not searching when user was selected. | J94: =IF(I94="New",0,G94-K94) -> 1 | L94: =IF(I94="New",G94,0) -> 0
A95: 46224 | B95: Reymart | C95: TBS_CALENDAR | D95: 2026JULY | E95: 1.6375 | F95: 1.7236111 | G95: 2.066666 | H95: Filing Type Enhancements: New feature - Added support for locking specific Excel cells via 'xlsx-js-style' library | J95: =IF(I95="New",0,G95-K95) -> 1.366666 | K95: 0.7 | L95: =IF(I95="New",G95,0) -> 0
A96: 46224 | B96: Reymart | C96: TBS_CALENDAR | D96: 2026JULY | E96: 1.7743056 | F96: 1.8652778 | G96: 2.183333 | H96: Bug Fix - FT_026 Open Filings: Enhanced FormController.cs by adding company name as default data for filing list display | J96: =IF(I96="New",0,G96-K96) -> 1.183333 | K96: 1 | L96: =IF(I96="New",G96,0) -> 0
A97: 46225 | B97: Reymart | C97: TBS_CALENDAR | D97: 2026JULY | E97: 1.3375 | F97: 1.425 | G97: 2.1 | H97: Bug Fix - Filing Type: Modified FilingTypeController.cs to add saving of import file within the main core import process | J97: =IF(I97="New",0,G97-K97) -> 1.1 | K97: 1 | L97: =IF(I97="New",G97,0) -> 0
A98: 46225 | B98: Reymart | C98: TBS_CALENDAR | D98: 2026JULY | E98: 1.425 | F98: 1.5159722 | G98: 2.183333 | H98: Bug Fix - Filing Type: Added new function appendObjectToFormData.ts to combine cfiling list/import file into a 1 request | J98: =IF(I98="New",0,G98-K98) -> 0.783333 | K98: 1.4 | L98: =IF(I98="New",G98,0) -> 0
A99: 46225 | B99: Reymart | C99: TBS_CALENDAR | D99: 2026JULY | E99: 1.5631944 | F99: 1.6486111 | G99: 2.05 | H99: Bug Fix - Filing Type: Enhanced frontend import functionality by adding file-saving capability to upload/import process | J99: =IF(I99="New",0,G99-K99) -> 0.65 | K99: 1.4 | L99: =IF(I99="New",G99,0) -> 0
A100: 46225 | B100: Reymart | C100: TBS_CALENDAR | D100: 2026JULY | E100: 1.6486111 | F100: 1.7354167 | G100: 2.083333 | H100: Bug Fix - Filing Type: Improved filing-type-service.ts by adopting FormData to support file inclusion in requests | J100: =IF(I100="New",0,G100-K100) -> 0.683333 | K100: 1.4 | L100: =IF(I100="New",G100,0) -> 0
A101: 46225 | B101: Benjie | C101: TBS_PRG | D101: 2026JUL | E101: 1.0083333 | F101: 1.0375 | G101: 0.7 | H101: 2026JUL: Work on testing if the tax rule restrictions | J101: =IF(I101="New",0,G101-K101) -> 0.7 | L101: =IF(I101="New",G101,0) -> 0
A102: 46225 | B102: Benjie | C102: TBS_PRG | D102: 2026JUL | E102: 1.0375 | F102: 1.0840278 | G102: 1.116666 | H102: 2026JUL: Started working on polishing the associated states for the state module. | I102: New | L102: =IF(I102="New",G102,0) -> 1.116666
A103: 46225 | B103: Benjie | C103: TBS_PRG | D103: 2026JUL | E103: 1.1166667 | F103: 1.1847222 | G103: 1.633333 | H103: 2026JUL: Worked on the company modal, change the positioning and layout of the fields | I103: New | L103: =IF(I103="New",G103,0) -> 1.633333
...

Sheet Sheet2
A1: Date
A2: 46204 | B2: =SUMIFS(Sheet1!G:G,Sheet1!B:B,"=Reymart",Sheet1!A:A,Sheet2!A2) -> 8.499999
A3: 46205 | B3: =SUMIFS(Sheet1!G:G,Sheet1!B:B,"=Reymart",Sheet1!A:A,Sheet2!A3) -> 8.649998
A4: 46206 | B4: =SUMIFS(Sheet1!G:G,Sheet1!B:B,"=Reymart",Sheet1!A:A,Sheet2!A4) -> 8.483331
A5: 46209 | B5: =SUMIFS(Sheet1!G:G,Sheet1!B:B,"=Reymart",Sheet1!A:A,Sheet2!A5) -> 8.633331
A6: 46210 | B6: =SUMIFS(Sheet1!G:G,Sheet1!B:B,"=Reymart",Sheet1!A:A,Sheet2!A6) -> 8.549999
A7: 46211 | B7: =SUMIFS(Sheet1!G:G,Sheet1!B:B,"=Reymart",Sheet1!A:A,Sheet2!A7) -> 8.533333
A8: 46212 | B8: =SUMIFS(Sheet1!G:G,Sheet1!B:B,"=Reymart",Sheet1!A:A,Sheet2!A8) -> 4.333333
A9: 46213 | B9: =SUMIFS(Sheet1!G:G,Sheet1!B:B,"=Reymart",Sheet1!A:A,Sheet2!A9) -> 0
A10: 46214 | B10: =SUMIFS(Sheet1!G:G,Sheet1!B:B,"=Reymart",Sheet1!A:A,Sheet2!A10) -> 0
A11: 46216 | B11: =SUMIFS(Sheet1!G:G,Sheet1!B:B,"=Reymart",Sheet1!A:A,Sheet2!A11) -> 4.233333
A12: 46217 | B12: =SUMIFS(Sheet1!G:G,Sheet1!B:B,"=Reymart",Sheet1!A:A,Sheet2!A12) -> 8.366665
A13: 46218 | B13: =SUMIFS(Sheet1!G:G,Sheet1!B:B,"=Reymart",Sheet1!A:A,Sheet2!A13) -> 8.449999
... A25: 46234 | B25: =SUMIFS(Sheet1!G:G,Sheet1!B:B,"=Reymart",Sheet1!A:A,Sheet2!A25) -> 4.149999
